README.md
setup.py
beautiful_repr/__init__.py
beautiful_repr.egg-info/PKG-INFO
beautiful_repr.egg-info/SOURCES.txt
beautiful_repr.egg-info/dependency_links.txt
beautiful_repr.egg-info/top_level.txt