Metadata-Version: 2.1
Name: beautiful-repr
Version: 0.0.3
Summary: Library for beautiful object formatting
Home-page: https://github.com/TheArtur128/Beautiful-repr
Author: Arthur
Author-email: s9339307190@gmail.com
License: UNKNOWN
Download-URL: https://github.com/TheArtur128/Beautiful-repr/archive/refs/heads/master.zip
Platform: UNKNOWN
Requires-Python: >=3.10
